Metadata-Version: 2.1
Name: httproxies
Version: 1.0
Summary: proxies to use in your tool.
Home-page: UNKNOWN
Author: helper
License: MIT
Keywords: style
Platform: UNKNOWN
Classifier: Development Status :: 5 - Production/Stable
